dangermode/__init__.py
dangermode/__main__.py
dangermode/app.py
dangermode/models.py
dangermode/routes.py
dangermode/static/images/logo.png
dangermode/suggestions.py
dangermode-0.3.0.dist-info/LICENSE
dangermode-0.3.0.dist-info/METADATA
dangermode-0.3.0.dist-info/WHEEL
dangermode-0.3.0.dist-info/RECORD
