Metadata-Version: 2.1
Name: dangermode
Version: 0.3.0
Summary: ChatGPT Danger Mode for Jupyter
Home-page: https://github.com/rgbkrk/dangermode
Author: Kyle Kelley
Author-email: rgbkrk@gmail.com
Requires-Python: >=3.9,<4.0
Classifier: Development Status :: 2 - Pre-Alpha
Classifier: Intended Audience :: Developers
Classifier: License :: OSI Approved :: BSD License
Classifier: Natural Language :: English
Classifier: Programming Language :: Python :: 3
Classifier: Programming Language :: Python :: 3.9
Classifier: Programming Language :: Python :: 3.10
Classifier: Programming Language :: Python :: 3.11
Classifier: Programming Language :: Python :: 3
Classifier: Programming Language :: Python :: 3.8
Classifier: Programming Language :: Python :: 3.9
Requires-Dist: fastapi (>=0.95.0,<0.96.0)
Requires-Dist: ipython (>=8.12.0,<9.0.0)
Requires-Dist: jupyter-console (>=6.6.3,<7.0.0)
Requires-Dist: uvicorn (>=0.21.1,<0.22.0)
